huaweicloudsdkcloudartifact/__init__.py
huaweicloudsdkcloudartifact/v2/__init__.py
huaweicloudsdkcloudartifact/v2/cloudartifact_async_client.py
huaweicloudsdkcloudartifact/v2/cloudartifact_client.py
huaweicloudsdkcloudartifact/v2/model/__init__.py
huaweicloudsdkcloudartifact/v2/model/release_file_version_do.py
huaweicloudsdkcloudartifact/v2/model/show_project_release_files_request.py
huaweicloudsdkcloudartifact/v2/model/show_project_release_files_response.py
huaweicloudsdkcloudartifact/v2/model/show_release_project_files_request.py
huaweicloudsdkcloudartifact/v2/model/show_release_project_files_response.py
huaweicloudsdkcloudartifact/v2/model/standard_response_result.py
huaweicloudsdkcloudartifact/v2/region/__init__.py
huaweicloudsdkcloudartifact/v2/region/cloudartifact_region.py
huaweicloudsdkcloudartifact-3.1.24.dist-info/LICENSE
huaweicloudsdkcloudartifact-3.1.24.dist-info/METADATA
huaweicloudsdkcloudartifact-3.1.24.dist-info/WHEEL
huaweicloudsdkcloudartifact-3.1.24.dist-info/top_level.txt
huaweicloudsdkcloudartifact-3.1.24.dist-info/RECORD
